EpubZhinanCongRumenDaoFangqiChini20190101Fix1/README.md
EpubZhinanCongRumenDaoFangqiChini20190101Fix1/__init__.py
EpubZhinanCongRumenDaoFangqiChini20190101Fix1/__main__.py
EpubZhinanCongRumenDaoFangqiChini20190101Fix1/file.epub
EpubZhinanCongRumenDaoFangqiChini20190101Fix1/index.html
EpubZhinanCongRumenDaoFangqiChini20190101Fix1/css/__init__.py
EpubZhinanCongRumenDaoFangqiChini20190101Fix1/css/annotations.css
EpubZhinanCongRumenDaoFangqiChini20190101Fix1/css/main.css
EpubZhinanCongRumenDaoFangqiChini20190101Fix1/css/normalize.css
EpubZhinanCongRumenDaoFangqiChini20190101Fix1/css/popup.css
EpubZhinanCongRumenDaoFangqiChini20190101Fix1/font/__init__.py
EpubZhinanCongRumenDaoFangqiChini20190101Fix1/font/fontello.eot
EpubZhinanCongRumenDaoFangqiChini20190101Fix1/font/fontello.svg
EpubZhinanCongRumenDaoFangqiChini20190101Fix1/font/fontello.ttf
EpubZhinanCongRumenDaoFangqiChini20190101Fix1/font/fontello.woff
EpubZhinanCongRumenDaoFangqiChini20190101Fix1/img/__init__.py
EpubZhinanCongRumenDaoFangqiChini20190101Fix1/img/annotator-glyph-sprite.png
EpubZhinanCongRumenDaoFangqiChini20190101Fix1/img/annotator-icon-sprite.png
EpubZhinanCongRumenDaoFangqiChini20190101Fix1/img/apple-touch-icon.png
EpubZhinanCongRumenDaoFangqiChini20190101Fix1/img/cancelfullscreen.png
EpubZhinanCongRumenDaoFangqiChini20190101Fix1/img/close.png
EpubZhinanCongRumenDaoFangqiChini20190101Fix1/img/fullscreen.png
EpubZhinanCongRumenDaoFangqiChini20190101Fix1/img/loader.gif
EpubZhinanCongRumenDaoFangqiChini20190101Fix1/img/menu-icon.png
EpubZhinanCongRumenDaoFangqiChini20190101Fix1/img/save.png
EpubZhinanCongRumenDaoFangqiChini20190101Fix1/img/saved.png
EpubZhinanCongRumenDaoFangqiChini20190101Fix1/img/settings-s.png
EpubZhinanCongRumenDaoFangqiChini20190101Fix1/img/settings.png
EpubZhinanCongRumenDaoFangqiChini20190101Fix1/img/star.png
EpubZhinanCongRumenDaoFangqiChini20190101Fix1/js/__init__.py
EpubZhinanCongRumenDaoFangqiChini20190101Fix1/js/epub.js
epub_zhinan_cong_rumen_dao_fangqi_chini_20190101_fix1-2025.3.24.0.dist-info/METADATA
epub_zhinan_cong_rumen_dao_fangqi_chini_20190101_fix1-2025.3.24.0.dist-info/WHEEL
epub_zhinan_cong_rumen_dao_fangqi_chini_20190101_fix1-2025.3.24.0.dist-info/entry_points.txt
epub_zhinan_cong_rumen_dao_fangqi_chini_20190101_fix1-2025.3.24.0.dist-info/top_level.txt
epub_zhinan_cong_rumen_dao_fangqi_chini_20190101_fix1-2025.3.24.0.dist-info/RECORD
